kharosthi/__init__.py
kharosthi/numbers.py
kharosthi.numbers-0.1.2.dist-info/WHEEL
kharosthi.numbers-0.1.2.dist-info/METADATA
kharosthi.numbers-0.1.2.dist-info/RECORD
