Metadata-Version: 2.1
Name: kharosthi.numbers
Version: 0.1.2
Summary: A module to represent kharosthi numbers
Home-page: https://github.com/ulrikjohansson/kharosthi_numbers
License: MIT
Author: Ulrik Johansson
Author-email: ulrik@ulrik.io
Requires-Python: >=3.6,<4.0
Classifier: License :: OSI Approved :: MIT License
Classifier: Programming Language :: Python :: 3
Classifier: Programming Language :: Python :: 3.6
Classifier: Programming Language :: Python :: 3.7
Classifier: Programming Language :: Python :: 3.8
Classifier: Programming Language :: Python :: 3.9
Project-URL: Repository, https://github.com/ulrikjohansson/kharosthi_numbers
